{
    "resultCount": 2,
    "results": [
        {
            "screenshotUrls": [
                "https://is1-ssl.mzstatic.com/image/thumb/Purple122/v4/70/f2/51/70f251fd-ae7a-5ef9-eda8-aa94fd077056/pr_source.png/392x696bb.png",
                "https://is3-ssl.mzstatic.com/image/thumb/Purple122/v4/3d/f4/90/3df4905e-53be-7686-11d1-4db5605076fc/pr_source.png/392x696bb.png",
                "https://is4-ssl.mzstatic.com/image/thumb/Purple111/v4/df/8b/59/df8b59e8-aeb6-f70c-af0f-fa56d6d0c8a5/pr_source.png/392x696bb.png",
                "https://is2-ssl.mzstatic.com/image/thumb/Purple122/v4/22/fc/97/22fc9705-ea7e-0ada-7dc5-2922f04e3d9b/pr_source.png/392x696bb.png",
                "https://is5-ssl.mzstatic.com/image/thumb/Purple122/v4/e8/a2/47/e8a2478d-1bed-d981-e865-9a0da9dc3c01/pr_source.png/392x696bb.png"
            ],
            "ipadScreenshotUrls": [],
            "appletvScreenshotUrls": [],
            "artworkUrl512": "https://is5-ssl.mzstatic.com/image/thumb/Purple71/v4/56/1f/7e/561f7e0d-ac7c-ce34-b964-33a7d0786ce3/source/512x512bb.jpg",
            "artworkUrl60": "https://is5-ssl.mzstatic.com/image/thumb/Purple71/v4/56/1f/7e/561f7e0d-ac7c-ce34-b964-33a7d0786ce3/source/60x60bb.jpg",
            "artworkUrl100": "https://is5-ssl.mzstatic.com/image/thumb/Purple71/v4/56/1f/7e/561f7e0d-ac7c-ce34-b964-33a7d0786ce3/source/100x100bb.jpg",
            "artistViewUrl": "https://apps.apple.com/us/developer/illusion-labs/id297694604?uo=4",
            "supportedDevices": [
                "Watch6Cellular-Watch6Cellular",
                "iPad74-iPad74",
                "iPhone8-iPhone8",
                "iPhone8Plus-iPhone8Plus",
                "iPhone11Pro-iPhone11Pro",
                "iPhoneXS-iPhoneXS",
                "iPadAir3-iPadAir3",
                "iPhoneSESecondGen-iPhoneSESecondGen",
                "iPhone7-iPhone7",
                "iPad612-iPad612",
                "iPad23G-iPad23G",
                "iPadPro97-iPadPro97",
                "iPadAir2Cellular-iPadAir2Cellular",
                "iPadMini3Cellular-iPadMini3Cellular",
                "WatchSE-WatchSE",
                "iPad878-iPad878",
                "iPad834-iPad834",
                "iPhone12Mini-iPhone12Mini",
                "iPad72-iPad72",
                "iPodTouchSixthGen-iPodTouchSixthGen",
                "iPhone12Pro-iPhone12Pro",
                "Watch6-Watch6",
                "iPadProCellular-iPadProCellular",
                "iPadMini5-iPadMini5",
                "iPhoneXR-iPhoneXR",
                "iPad611-iPad611",
                "iPhoneXSMax-iPhoneXSMax",
                "iPhone12ProMax-iPhone12ProMax",
                "iPhone7Plus-iPhone7Plus",
                "iPadEighthGen-iPadEighthGen",
                "iPadAirCellular-iPadAirCellular",
                "iPadMini3-iPadMini3",
                "iPhone6sPlus-iPhone6sPlus",
                "iPadAir4-iPadAir4",
                "iPadProSecondGenCellular-iPadProSecondGenCellular",
                "iPhone6Plus-iPhone6Plus",
                "iPhone12-iPhone12",
                "iPodTouchFifthGen-iPodTouchFifthGen",
                "iPhone11-iPhone11",
                "iPadPro97Cellular-iPadPro97Cellular",
                "Watch4-Watch4",
                "iPadMini-iPadMini",
                "iPadAir-iPadAir",
                "iPadMini4G-iPadMini4G",
                "iPadMiniRetinaCellular-iPadMiniRetinaCellular",
                "iPhoneSE-iPhoneSE",
                "iPhone5s-iPhone5s",
                "iPad73-iPad73",
                "iPadMini5Cellular-iPadMini5Cellular",
                "iPadPro-iPadPro",
                "iPhone6-iPhone6",
                "iPadAir2-iPadAir2",
                "iPhone6s-iPhone6s",
                "iPadSeventhGenCellular-iPadSeventhGenCellular",
                "iPhone5-iPhone5",
                "iPadProFourthGen-iPadProFourthGen",
                "iPadProFourthGenCellular-iPadProFourthGenCellular",
                "iPadMiniRetina-iPadMiniRetina",
                "iPadProSecondGen-iPadProSecondGen",
                "iPadMini4-iPadMini4",
                "iPad812-iPad812",
                "iPodTouchSeventhGen-iPodTouchSeventhGen",
                "iPadFourthGen4G-iPadFourthGen4G",
                "iPhone11ProMax-iPhone11ProMax",
                "iPhoneX-iPhoneX",
                "iPadEighthGenCellular-iPadEighthGenCellular",
                "iPadFourthGen-iPadFourthGen",
                "iPadAir4Cellular-iPadAir4Cellular",
                "iPadThirdGen-iPadThirdGen",
                "iPad76-iPad76",
                "iPadSeventhGen-iPadSeventhGen",
                "iPad71-iPad71",
                "iPhone5c-iPhone5c",
                "iPadMini4Cellular-iPadMini4Cellular",
                "iPad75-iPad75",
                "iPadThirdGen4G-iPadThirdGen4G",
                "Watch5-Watch5",
                "iPhone4S-iPhone4S",
                "iPad2Wifi-iPad2Wifi",
                "iPadAir3Cellular-iPadAir3Cellular",
                "WatchSECellular-WatchSECellular",
                "iPad856-iPad856"
            ],
            "advisories": [],
            "isGameCenterEnabled": true,
            "features": [
                "gameCenter"
            ],
            "kind": "software",
            "currency": "USD",
            "languageCodesISO2A": [
                "EN"
            ],
            "fileSizeBytes": "31086592",
            "sellerUrl": "http://www.labyrinth2.com",
            "averageUserRatingForCurrentVersion": 4.4375,
            "userRatingCountForCurrentVersion": 32,
            "trackContentRating": "4+",
            "contentAdvisoryRating": "4+",
            "trackCensoredName": "Labyrinth 2 Lite",
            "trackViewUrl": "https://apps.apple.com/us/app/labyrinth-2-lite/id350765814?uo=4",
            "averageUserRating": 4.4375,
            "releaseDate": "2010-01-20T00:14:26Z",
            "formattedPrice": "Free",
            "genreIds": [
                "6014",
                "7012",
                "6016",
                "7003"
            ],
            "primaryGenreName": "Games",
            "isVppDeviceBasedLicensingEnabled": true,
            "currentVersionReleaseDate": "2017-01-19T09:23:21Z",
            "releaseNotes": "Optimized for iOS 10",
            "sellerName": "Illusion Labs AB",
            "minimumOsVersion": "8.0",
            "primaryGenreId": 6014,
            "description": "See video trailer here: http://trailer.labyrinth2.com\n\n\"Labyrinth 2 is one of the absolutely very best games in the App Store. I didn’t know Labyrinth could be this deluxe, fun, challenging, easy, and addicting. Illusion Labs gives you absolutely everything with great levels already made, a level editor, local multiplayer, and access to a potentially limitless supply of more levels.\"\n- App Advice\n\n\"If you've enjoyed labyrinth games in the past, Labyrinth 2 is a must-own.\"\n- Touch Arcade\n\n\"It looks and plays like the real thing, with just the right number of additional features to elevate it high above the physical toy.\"\n- Pocket Gamer\n\n---------------------------------------------\n\nThe creators of the original iPhone Labyrinth game bring you Labyrinth 2 Lite - the groundbreaking game taken to the next level.\n\n- New game elements: Cannons, Bumpers, Multiple balls, Doors, Magnets, Fans, Resizers, Merry-Go-Rounds, Duplicators, Lasers and more...\n- Up to 4 player multiplayer over Wi-Fi or Bluetooth\n- Compete against yourself with a ghost ball showing your best run\n- Awards for your achievements\n- Create and play your own levels\n\nFollow @illusionlabs on Twitter\nLike us at www.facebook.com/illusionlabs1",
            "trackId": 350765814,
            "trackName": "Labyrinth 2 Lite",
            "price": 0.0,
            "artistId": 297694604,
            "artistName": "Illusion Labs",
            "genres": [
                "Games",
                "Puzzle",
                "Entertainment",
                "Casual"
            ],
            "bundleId": "se.illusionlabs.labyrinth2lite",
            "version": "1.7.0",
            "wrapperType": "software",
            "userRatingCount": 32
        },
        {
            "screenshotUrls": [
                "https://is5-ssl.mzstatic.com/image/thumb/Purple111/v4/dd/16/b0/dd16b045-7bd5-9058-88e2-f7f649194cf8/pr_source.png/392x696bb.png",
                "https://is2-ssl.mzstatic.com/image/thumb/Purple111/v4/a8/8f/04/a88f0414-5dda-cc59-a63b-552203b2d32e/pr_source.png/392x696bb.png",
                "https://is3-ssl.mzstatic.com/image/thumb/Purple122/v4/47/91/5a/47915af3-a014-a78d-e792-603fee10972e/pr_source.png/392x696bb.png",
                "https://is3-ssl.mzstatic.com/image/thumb/Purple122/v4/ec/a2/92/eca29222-5178-f642-cc3e-2fc3c097f2df/pr_source.png/392x696bb.png",
                "https://is5-ssl.mzstatic.com/image/thumb/Purple122/v4/63/df/06/63df06ed-8290-2323-eebc-9a1078f52168/pr_source.png/392x696bb.png"
            ],
            "ipadScreenshotUrls": [],
            "appletvScreenshotUrls": [],
            "artworkUrl512": "https://is5-ssl.mzstatic.com/image/thumb/Purple62/v4/ea/e6/b4/eae6b4a9-46c6-5bb0-e408-6f81a18eaad0/source/512x512bb.jpg",
            "artworkUrl60": "https://is5-ssl.mzstatic.com/image/thumb/Purple62/v4/ea/e6/b4/eae6b4a9-46c6-5bb0-e408-6f81a18eaad0/source/60x60bb.jpg",
            "artworkUrl100": "https://is5-ssl.mzstatic.com/image/thumb/Purple62/v4/ea/e6/b4/eae6b4a9-46c6-5bb0-e408-6f81a18eaad0/source/100x100bb.jpg",
            "artistViewUrl": "https://apps.apple.com/us/developer/illusion-labs/id297694604?uo=4",
            "supportedDevices": [
                "Watch6Cellular-Watch6Cellular",
                "iPad74-iPad74",
                "iPhone8-iPhone8",
                "iPhone8Plus-iPhone8Plus",
                "iPhone11Pro-iPhone11Pro",
                "iPhoneXS-iPhoneXS",
                "iPadAir3-iPadAir3",
                "iPhoneSESecondGen-iPhoneSESecondGen",
                "iPhone7-iPhone7",
                "iPad612-iPad612",
                "iPad23G-iPad23G",
                "iPadPro97-iPadPro97",
                "iPadAir2Cellular-iPadAir2Cellular",
                "iPadMini3Cellular-iPadMini3Cellular",
                "WatchSE-WatchSE",
                "iPad878-iPad878",
                "iPad834-iPad834",
                "iPhone12Mini-iPhone12Mini",
                "iPad72-iPad72",
                "iPodTouchSixthGen-iPodTouchSixthGen",
                "iPhone12Pro-iPhone12Pro",
                "Watch6-Watch6",
                "iPadProCellular-iPadProCellular",
                "iPadMini5-iPadMini5",
                "iPhoneXR-iPhoneXR",
                "iPad611-iPad611",
                "iPhoneXSMax-iPhoneXSMax",
                "iPhone12ProMax-iPhone12ProMax",
                "iPhone7Plus-iPhone7Plus",
                "iPadEighthGen-iPadEighthGen",
                "iPadAirCellular-iPadAirCellular",
                "iPadMini3-iPadMini3",
                "iPhone6sPlus-iPhone6sPlus",
                "iPadAir4-iPadAir4",
                "iPadProSecondGenCellular-iPadProSecondGenCellular",
                "iPhone6Plus-iPhone6Plus",
                "iPhone12-iPhone12",
                "iPodTouchFifthGen-iPodTouchFifthGen",
                "iPhone11-iPhone11",
                "iPadPro97Cellular-iPadPro97Cellular",
                "Watch4-Watch4",
                "iPadMini-iPadMini",
                "iPadAir-iPadAir",
                "iPadMini4G-iPadMini4G",
                "iPadMiniRetinaCellular-iPadMiniRetinaCellular",
                "iPhoneSE-iPhoneSE",
                "iPhone5s-iPhone5s",
                "iPad73-iPad73",
                "iPadMini5Cellular-iPadMini5Cellular",
                "iPadPro-iPadPro",
                "iPhone6-iPhone6",
                "iPadAir2-iPadAir2",
                "iPhone6s-iPhone6s",
                "iPadSeventhGenCellular-iPadSeventhGenCellular",
                "iPhone5-iPhone5",
                "iPadProFourthGen-iPadProFourthGen",
                "iPadProFourthGenCellular-iPadProFourthGenCellular",
                "iPadMiniRetina-iPadMiniRetina",
                "iPadProSecondGen-iPadProSecondGen",
                "iPadMini4-iPadMini4",
                "iPad812-iPad812",
                "iPodTouchSeventhGen-iPodTouchSeventhGen",
                "iPadFourthGen4G-iPadFourthGen4G",
                "iPhone11ProMax-iPhone11ProMax",
                "iPhoneX-iPhoneX",
                "iPadEighthGenCellular-iPadEighthGenCellular",
                "iPadFourthGen-iPadFourthGen",
                "iPadAir4Cellular-iPadAir4Cellular",
                "iPadThirdGen-iPadThirdGen",
                "iPad76-iPad76",
                "iPadSeventhGen-iPadSeventhGen",
                "iPad71-iPad71",
                "iPhone5c-iPhone5c",
                "iPadMini4Cellular-iPadMini4Cellular",
                "iPad75-iPad75",
                "iPadThirdGen4G-iPadThirdGen4G",
                "Watch5-Watch5",
                "iPhone4S-iPhone4S",
                "iPad2Wifi-iPad2Wifi",
                "iPadAir3Cellular-iPadAir3Cellular",
                "WatchSECellular-WatchSECellular",
                "iPad856-iPad856"
            ],
            "advisories": [],
            "isGameCenterEnabled": true,
            "features": [
                "gameCenter"
            ],
            "kind": "software",
            "currency": "USD",
            "languageCodesISO2A": [
                "EN"
            ],
            "fileSizeBytes": "29882368",
            "sellerUrl": "http://www.labyrinth2.com",
            "averageUserRatingForCurrentVersion": 4.41667,
            "userRatingCountForCurrentVersion": 24,
            "trackContentRating": "4+",
            "contentAdvisoryRating": "4+",
            "trackCensoredName": "Labyrinth 2",
            "trackViewUrl": "https://apps.apple.com/us/app/labyrinth-2/id307758884?uo=4",
            "averageUserRating": 4.41667,
            "releaseDate": "2009-12-01T20:29:25Z",
            "formattedPrice": "$4.99",
            "genreIds": [
                "6014",
                "7012",
                "6016",
                "7003"
            ],
            "primaryGenreName": "Games",
            "isVppDeviceBasedLicensingEnabled": true,
            "currentVersionReleaseDate": "2017-01-19T09:23:02Z",
            "releaseNotes": "Optimized for iOS 10",
            "sellerName": "Illusion Labs AB",
            "minimumOsVersion": "8.0",
            "primaryGenreId": 6014,
            "description": "See video trailer here: http://trailer.labyrinth2.com\n\n\"Labyrinth 2 is one of the absolutely very best games in the App Store. I didn’t know Labyrinth could be this deluxe, fun, challenging, easy, and addicting. Illusion Labs gives you absolutely everything with great levels already made, a level editor, local multiplayer, and access to a potentially limitless supply of more levels.\"\n- App Advice\n\n\"If you've enjoyed labyrinth games in the past, Labyrinth 2 is a must-own.\"\n- Touch Arcade\n\n\"It looks and plays like the real thing, with just the right number of additional features to elevate it high above the physical toy.\"\n- Pocket Gamer\n\n---------------------------------------------\n\nThe creators of the original iPhone Labyrinth game bring you Labyrinth 2 - the groundbreaking game taken to the next level.\n\n- New game elements: Cannons, Bumpers, Multiple balls, Doors, Magnets, Fans, Resizers, Merry-Go-Rounds, Duplicators, Lasers and more...\n- Create your own levels and share them instantly with your friends and the world\n- Download and rate levels created by the community\n- Up to 4 player multiplayer over Wi-Fi or Bluetooth\n- Compete against yourself with a ghost ball showing your best run\n- Awards for your achievements\n\nFollow @illusionlabs on Twitter\nLike us at www.facebook.com/illusionlabs1",
            "trackId": 307758884,
            "trackName": "Labyrinth 2",
            "price": 4.99,
            "artistId": 297694604,
            "artistName": "Illusion Labs",
            "genres": [
                "Games",
                "Puzzle",
                "Entertainment",
                "Casual"
            ],
            "bundleId": "se.illusionlabs.labyrinth2",
            "version": "1.7.0",
            "wrapperType": "software",
            "userRatingCount": 24
        }
    ]
}